linkedin_jobs_pyscraper/__init__.py
linkedin_jobs_pyscraper/linkedin_jobs_scraper.py
linkedin_jobs_pyscraper/extract/__init__.py
linkedin_jobs_pyscraper/extract/extract_job_info.py
linkedin_jobs_pyscraper/models/__init__.py
linkedin_jobs_pyscraper/models/extract/__init__.py
linkedin_jobs_pyscraper/models/extract/extractor.py
linkedin_jobs_pyscraper/models/filters/__init__.py
linkedin_jobs_pyscraper/models/filters/filters.py
linkedin_jobs_pyscraper/models/job/__init__.py
linkedin_jobs_pyscraper/models/job/job.py
linkedin_jobs_pyscraper/models/search/__init__.py
linkedin_jobs_pyscraper/models/search/searcher.py
linkedin_jobs_pyscraper/search/__init__.py
linkedin_jobs_pyscraper/search/search_jobs.py
linkedin_jobs_pyscraper/utils/__init__.py
linkedin_jobs_pyscraper/utils/helpers.py
multilingual_pdf2text/__init__.py
multilingual_pdf2text/pdf2text.py
multilingual_pdf2text/doc2img/__init__.py
multilingual_pdf2text/doc2img/parse_document.py
multilingual_pdf2text/models/__init__.py
multilingual_pdf2text/models/document_model/__init__.py
multilingual_pdf2text/models/document_model/document.py
multilingual_pdf2text/ocr/__init__.py
multilingual_pdf2text/ocr/image_to_text.py
multilingual_pdf2text-1.1.0.dist-info/LICENSE
multilingual_pdf2text-1.1.0.dist-info/METADATA
multilingual_pdf2text-1.1.0.dist-info/WHEEL
multilingual_pdf2text-1.1.0.dist-info/top_level.txt
multilingual_pdf2text-1.1.0.dist-info/RECORD
