Metadata-Version: 2.1
Name: multilingual-pdf2text
Version: 1.1.0
Summary: A python library for extracting text from PDFs without losing the formatting of the PDF content.
Home-page: https://github.com/shahrukhx01/multilingual-pdf2text
Author: Shahrukh Khan
Author-email: sk28671@gmail.com
License: UNKNOWN
Platform: UNKNOWN
Classifier: Intended Audience :: Developers
Classifier: Programming Language :: Python
Classifier: Programming Language :: Python :: 3.6
Classifier: License :: OSI Approved :: MIT License
Classifier: Operating System :: OS Independent
Requires-Python: >=3.6
Requires-Dist: pydantic
Requires-Dist: pytesseract
Requires-Dist: pdf2image
Requires-Dist: pillow
